api_canvas_lms/__init__.py
api_canvas_lms/account.py
api_canvas_lms/adda.py
api_canvas_lms/base.py
api_canvas_lms/course.py
api_canvas_lms/discussion_topic.py
api_canvas_lms/enrollment.py
api_canvas_lms/exceptions.py
api_canvas_lms/module.py
api_canvas_lms/mvc.py
api_canvas_lms/user.py
api_canvas_lms/utils.py
api_canvas_lms-0.1.30.dist-info/LICENSE
api_canvas_lms-0.1.30.dist-info/METADATA
api_canvas_lms-0.1.30.dist-info/WHEEL
api_canvas_lms-0.1.30.dist-info/top_level.txt
api_canvas_lms-0.1.30.dist-info/RECORD
