Metadata-Version: 2.1
Name: api-canvas-lms
Version: 0.1.30
Summary: Una biblioteca de Python para Canvas LMS
Home-page: https://github.com/jgomezz/api_canvas_lms
Author: Jaime Gomez
Author-email: jgomezz@gmail.com
License-File: LICENSE
